mediaman/config.py
mediaman-0.0.1.dist-info/LICENSE
mediaman-0.0.1.dist-info/METADATA
mediaman-0.0.1.dist-info/WHEEL
mediaman-0.0.1.dist-info/entry_points.txt
mediaman-0.0.1.dist-info/top_level.txt
mediaman-0.0.1.dist-info/RECORD
