Metadata-Version: 2.1
Name: mediaman
Version: 0.0.1
Summary: MediaMan backs up arbitrary media files to arbitrary cloud services!
Home-page: https://github.com/MattCCS/MediaMan
Author: Matt Cotton
Author-email: matthewcotton.cs@gmail.com
License: UNKNOWN
Platform: UNKNOWN
Classifier: Programming Language :: Python :: 3
